glob_utils/__init__.py
glob_utils/_decorators.py
glob_utils/_exceptions.py
glob_utils/_proxy.py
glob_utils/apiClient.py
glob_utils/eventSource.py
glob_utils/typedef.py
glob_utils/utils.py
glob_utils-0.0.6.dist-info/METADATA
glob_utils-0.0.6.dist-info/WHEEL
glob_utils-0.0.6.dist-info/RECORD
